viral_usher/build.py
viral_usher/cli.py
viral_usher/config.py
viral_usher/init.py
viral_usher/ncbi_helper.py
viral_usher/nextclade_helper.py
viral_usher/viral_usher_build.py
viral_usher-0.10.1.dist-info/licenses/LICENSE
viral_usher-0.10.1.dist-info/METADATA
viral_usher-0.10.1.dist-info/WHEEL
viral_usher-0.10.1.dist-info/entry_points.txt
viral_usher-0.10.1.dist-info/top_level.txt
viral_usher-0.10.1.dist-info/RECORD
