Metadata-Version: 2.4
Name: viral_usher
Version: 0.10.1
Summary: Easily configure and run a pipeline to build a tree of virus genomes using UShER
Author-email: Angie Hinrichs <hinrichs@ucsc.edu>
License-Expression: MIT
Project-URL: Homepage, https://github.com/AngieHinrichs/viral_usher
Project-URL: Issues, https://github.com/AngieHinrichs/viral_usher/issues
Classifier: Programming Language :: Python :: 3
Classifier: Operating System :: OS Independent
Requires-Python: >=3.11
License-File: LICENSE
Requires-Dist: requests
Requires-Dist: biopython
Requires-Dist: docker
Dynamic: license-file
